mara_page/__init__.py
mara_page/acl.py
mara_page/bootstrap.py
mara_page/html.py
mara_page/navigation.py
mara_page/response.py
mara_page/xml.py
mara_page-1.7.0.dist-info/LICENSE
mara_page-1.7.0.dist-info/METADATA
mara_page-1.7.0.dist-info/WHEEL
mara_page-1.7.0.dist-info/top_level.txt
mara_page-1.7.0.dist-info/RECORD
