Metadata-Version: 2.1
Name: mara-page
Version: 1.7.0
Summary: Minimal API for defining pages of Flask-based backends independently from the actual backend infrastructure
Home-page: https://github.com/mara/mara-page
Author: Mara contributors
License: MIT
Requires-Python: >=3.6
License-File: LICENSE
Requires-Dist: flask (>=0.12)
Requires-Dist: pygments (>=2.2.0)
